<Skill Loop="0">
  <TimeLines Type="3" TypeName="Action">
    <Frame Point="0">
      <Action Operation="TurnOn" ActionName="Skill" Speed="1" ActionFileLegth="1.3" BackPos="0,0,0" BackTime="1" StayTime="1" RecoveryTime="1" DisableHeadIK="False" DisableBodyIK="False" />
    </Frame>
  </TimeLines>
  <TimeLines Type="2" TypeName="Effect">
    <Frame Point="0">
      <Action Operation="TurnOn" EffectPath="EffectPerfab\Skill\ZhenFu_BigAttack" BonePoint="" EffectName="xuli" LifeTime="-1" AutoDestroy="True" BuildBone="True" AutoScale="True" ZeroPos="False" />
    </Frame>
  </TimeLines>
  <TimeLines Type="0" TypeName="Launch">
    <Frame Point="1">
      <Action Operation="TurnOn" LaunchPath="Launch\Launch_HERO_zhenfu_BigAttack" BonePoint="" HitCond="-1" AsFinish="True" Speed="30" LaunchDirection="-1" HitEffectName="" SkillId="-1" />
    </Frame>
  </TimeLines>
  <TimeLines Type="1" TypeName="Sound">
    <Frame Point="0.04">
      <Action Operation="TurnOn" SoundPath="SkillSound/DiaoChanAttack" SoundName="DiaoChanAttack" Loop="False" Volume="100" />
    </Frame>
    <Frame Point="0.4">
      <Action Operation="TurnOn" SoundPath="SkillSound/LiuBeiLight" SoundName="LiuBeiLight" Loop="False" Volume="100" />
    </Frame>
    <Frame Point="0.8">
      <Action Operation="TurnOn" SoundPath="SkillSound/SunQuanHit" SoundName="SunQuanHit" Loop="False" Volume="100" />
    </Frame>
    <Frame Point="1">
      <Action Operation="TurnOn" SoundPath="SkillSound/ZhaoYunLunQiang" SoundName="ZhaoYunLunQiang" Loop="False" Volume="100" />
    </Frame>
  </TimeLines>
</Skill>